lux/__init__.py
lux/lux.py
lux/metrics.py
lux/samplers.py
lux/pyuid3/__init__.py
lux/pyuid3/att_stats.py
lux/pyuid3/attribute.py
lux/pyuid3/data.py
lux/pyuid3/data_scrambler.py
lux/pyuid3/entropy_evaluator.py
lux/pyuid3/instance.py
lux/pyuid3/parse_exception.py
lux/pyuid3/reading.py
lux/pyuid3/tree.py
lux/pyuid3/tree_edge.py
lux/pyuid3/tree_evaluator.py
lux/pyuid3/tree_node.py
lux/pyuid3/uid3.py
lux/pyuid3/utils.py
lux/pyuid3/value.py
lux_explainer-1.3.2.dist-info/LICENSE
lux_explainer-1.3.2.dist-info/METADATA
lux_explainer-1.3.2.dist-info/WHEEL
lux_explainer-1.3.2.dist-info/top_level.txt
lux_explainer-1.3.2.dist-info/RECORD
