Metadata-Version: 2.1
Name: lux-explainer
Version: 1.3.2
Summary: Universal Local Rule-based Explainer
Author-email: Szymon Bobek <szymon.bobek@gmail.com>
License: MIT License
Project-URL: Homepage, https://github.com/sbobek/lux
Project-URL: Documentation, https://lux-explainer.readthedocs.org
Project-URL: Issues, https://github.com/sbobek/lux/issues
Keywords: xai,explainability,model-agnostic,rule-based
Classifier: License :: OSI Approved :: MIT License
Classifier: Programming Language :: Python
Classifier: Programming Language :: Python :: 3
Requires-Python: >=3.8
License-File: LICENSE
Requires-Dist: pandas>=1.4.3
Requires-Dist: numpy>=1.22.4
Requires-Dist: scikit-learn>=1.1.1
Requires-Dist: matplotlib>=3.5.2
Requires-Dist: matplotlib-inline>=0.1.3
Requires-Dist: seaborn>=0.11.2
Requires-Dist: graphviz>=0.20
Requires-Dist: shap>=0.41.0
Requires-Dist: imbalanced-learn>=0.9.1
Requires-Dist: gower-multiprocessing>=0.2.2
Requires-Dist: numdifftools>=0.9.41
